homf/__init__.py
homf/__main__.py
homf/cli.py
homf/version.py
homf/api/__init__.py
homf/api/asset_manager.py
homf/api/github.py
homf/api/pypi.py
homf-1.1.1.dist-info/METADATA
homf-1.1.1.dist-info/WHEEL
homf-1.1.1.dist-info/entry_points.txt
homf-1.1.1.dist-info/licenses/LICENSE.txt
homf-1.1.1.dist-info/RECORD
