Metadata-Version: 2.3
Name: homf
Version: 1.1.1
Summary: Download artifacts from various sources. E.g., a ZipApp from GitHub Releases.
Project-URL: repository, https://github.com/duckinator/homf
Project-URL: documentation, https://homf.readthedocs.io/en/latest/
Author-email: Ellen Marie Dash <me@duckie.co>
License: MIT
License-File: LICENSE.txt
Classifier: License :: OSI Approved :: MIT License
Classifier: Operating System :: OS Independent
Classifier: Programming Language :: Python :: 3
Classifier: Programming Language :: Python :: 3.8
Classifier: Programming Language :: Python :: 3.9
Classifier: Programming Language :: Python :: 3.10
Classifier: Programming Language :: Python :: 3.11
Requires-Python: >=3.8
Requires-Dist: packaging~=23.2
Provides-Extra: docs
Requires-Dist: sphinx; extra == 'docs'
Requires-Dist: sphinx-argparse; extra == 'docs'
Requires-Dist: sphinx-rtd-theme; extra == 'docs'
Provides-Extra: lint
Requires-Dist: pylint==3.0.1; extra == 'lint'
Provides-Extra: test
Requires-Dist: pytest==7.4.2; extra == 'test'
